{
    "data": [
        {
            "created_at": "2022-02-12T14:53:17.000Z",
            "id": "1492512028682067972",
            "name": "Lars Thiele",
            "username": "LarsThiele7"
        },
        {
            "created_at": "2009-06-30T06:51:36.000Z",
            "id": "52328776",
            "name": "Unidos x Venezuela",
            "username": "campoelias07"
        },
        {
            "created_at": "2022-02-12T13:05:17.000Z",
            "id": "1492484895779991553",
            "name": "Utsab Jung Chhetry",
            "username": "ChhetryUtsab"
        },
        {
            "created_at": "2022-02-12T14:49:45.000Z",
            "id": "1492511182418182144",
            "name": "Jm Torres",
            "username": "JmTorre41335717"
        },
        {
            "created_at": "2022-02-12T14:52:00.000Z",
            "id": "1492511754429112326",
            "name": "Anonymous",
            "username": "Anonymo32220733"
        },
        {
            "created_at": "2021-12-02T22:41:07.000Z",
            "id": "1466537819699040258",
            "name": "Mario",
            "username": "MrMassa316"
        },
        {
            "created_at": "2022-02-12T14:49:12.000Z",
            "id": "1492511043112820741",
            "name": "Øsisris",
            "username": "Osisuris"
        },
        {
            "created_at": "2022-02-12T14:52:13.000Z",
            "id": "1492511820296470529",
            "name": "natalia Briceño Tapia",
            "username": "natibri91"
        },
        {
            "created_at": "2017-01-25T11:56:51.000Z",
            "id": "824224512631783424",
            "name": "Svyatoslav Leonov",
            "username": "Un_L1ke"
        },
        {
            "created_at": "2022-02-12T14:51:43.000Z",
            "id": "1492511701807210496",
            "name": "何谦",
            "username": "hq185413815"
        },
        {
            "created_at": "2022-02-12T14:26:24.000Z",
            "id": "1492505001368997890",
            "name": "Andrew Laton",
            "username": "andrew6laton"
        },
        {
            "created_at": "2020-06-03T14:18:03.000Z",
            "id": "1268185101118001152",
            "name": "BearlyBaton9583",
            "username": "bearly9583"
        },
        {
            "created_at": "2022-02-12T12:39:14.000Z",
            "id": "1492478323800571905",
            "name": "Almuspik49",
            "username": "almuspik49"
        },
        {
            "created_at": "2021-08-07T07:30:51.000Z",
            "id": "1423909181103296515",
            "name": "︎ ︎ ︎ ︎",
            "username": "duvreft"
        },
        {
            "created_at": "2022-02-12T14:52:33.000Z",
            "id": "1492511826306809858",
            "name": "Kamil Borzuchowski",
            "username": "KBorzuchowski"
        },
        {
            "created_at": "2022-02-12T14:45:22.000Z",
            "id": "1492510006620692480",
            "name": "Enes Dağlı",
            "username": "enes_dglx"
        },
        {
            "created_at": "2022-02-12T14:51:10.000Z",
            "id": "1492511502536146948",
            "name": "Shisir",
            "username": "Shisir22"
        },
        {
            "created_at": "2022-02-12T14:45:21.000Z",
            "id": "1492510039545769986",
            "name": "Isaac Duenas",
            "username": "epiceyezac"
        },
        {
            "created_at": "2022-02-12T14:49:05.000Z",
            "id": "1492511037706416130",
            "name": "Johnny Perisic",
            "username": "JPerisic"
        },
        {
            "created_at": "2022-02-12T14:43:46.000Z",
            "id": "1492509448350625794",
            "name": "Rhlplgdc",
            "username": "Rdlcghlp"
        },
        {
            "created_at": "2022-02-12T14:49:26.000Z",
            "id": "1492511068119314433",
            "name": "Almadi Isak",
            "username": "AlmadiIsak"
        },
        {
            "created_at": "2022-02-12T14:48:38.000Z",
            "id": "1492510896089964545",
            "name": "Yassine atef",
            "username": "ElecAtef"
        },
        {
            "created_at": "2022-02-12T14:49:31.000Z",
            "id": "1492511118920916992",
            "name": "Shafiul Alam Fahim",
            "username": "ShafiulAlamFah2"
        },
        {
            "created_at": "2022-01-15T05:26:52.000Z",
            "id": "1482222594762092545",
            "name": "Aalekh Bhandari",
            "username": "Beasthunter_ab"
        },
        {
            "created_at": "2013-04-21T13:25:25.000Z",
            "id": "1369546836",
            "name": "Toriffix",
            "username": "Toriffix_"
        },
        {
            "created_at": "2022-02-11T15:06:10.000Z",
            "id": "1492152837404565511",
            "name": "GABRIEL SILVA",
            "username": "GABRIEL36703992"
        },
        {
            "created_at": "2022-02-12T14:44:00.000Z",
            "id": "1492509729884618758",
            "name": "Muhammad Hussain Atif",
            "username": "M_H_Aatif"
        },
        {
            "created_at": "2022-02-12T14:50:14.000Z",
            "id": "1492511310042439683",
            "name": "Lucy Dutton",
            "username": "lucydut090"
        },
        {
            "created_at": "2022-02-12T14:40:40.000Z",
            "id": "1492508889711104014",
            "name": "@Bittencourt, O Único Canal uma Viagem",
            "username": "Unicobom"
        },
        {
            "created_at": "2018-12-24T10:10:55.000Z",
            "id": "1077144582238793729",
            "name": "Harshil Patel",
            "username": "Harshilpatel03"
        },
        {
            "created_at": "2021-06-22T22:11:14.000Z",
            "id": "1407461149088571392",
            "name": "SeerCol",
            "username": "ColSeer"
        },
        {
            "created_at": "2022-02-12T14:47:20.000Z",
            "id": "1492510484909670402",
            "name": "Jose Moreira",
            "username": "mor18799347"
        },
        {
            "created_at": "2022-02-12T14:39:06.000Z",
            "id": "1492508483840843786",
            "name": "Donna M Reid",
            "username": "DonnaMReid2"
        },
        {
            "created_at": "2022-02-12T14:38:13.000Z",
            "id": "1492508204794003459",
            "name": "Tushar",
            "username": "Tushar310890"
        },
        {
            "created_at": "2022-02-12T14:27:35.000Z",
            "id": "1492505576475365380",
            "name": "girish raheja",
            "username": "girishraheja111"
        },
        {
            "created_at": "2022-02-12T14:47:12.000Z",
            "id": "1492510520024317952",
            "name": "SugarBox",
            "username": "SugarBoxMoney"
        },
        {
            "created_at": "2022-02-12T14:41:34.000Z",
            "id": "1492509057894301696",
            "name": "American_Muslim",
            "username": "NaGod408"
        },
        {
            "created_at": "2020-11-14T14:05:54.000Z",
            "id": "1327613662878724096",
            "name": "Ahmet Batuhan Şahin",
            "username": "Sahinbatu2007"
        },
        {
            "created_at": "2022-02-12T14:43:59.000Z",
            "id": "1492509613509558281",
            "name": "Dhiman Barua Durjoy",
            "username": "dhiman_durjoy"
        },
        {
            "created_at": "2022-02-12T14:49:03.000Z",
            "id": "1492510937974251525",
            "name": "Deeper Holand",
            "username": "DeeperHoland"
        },
        {
            "created_at": "2022-02-12T14:36:16.000Z",
            "id": "1492507791294025734",
            "name": "Alex Ng",
            "username": "AlexNg9399"
        },
        {
            "created_at": "2022-02-12T14:49:30.000Z",
            "id": "1492511101854093319",
            "name": "yavuzselim3460",
            "username": "YavuzSelim6034"
        },
        {
            "created_at": "2022-02-12T14:45:22.000Z",
            "id": "1492510035557158915",
            "name": "Harry Mc Coy",
            "username": "harry_mc_coy"
        },
        {
            "created_at": "2020-08-02T13:36:55.000Z",
            "id": "1289917970123300865",
            "name": "AB Waris Warasta",
            "username": "Ab_Warasta"
        },
        {
            "created_at": "2012-10-03T00:11:49.000Z",
            "id": "858922675",
            "name": "Katie",
            "username": "katiesfunny"
        },
        {
            "created_at": "2022-02-12T14:32:17.000Z",
            "id": "1492506802075938822",
            "name": "Otávio",
            "username": "Otavius2021"
        },
        {
            "created_at": "2022-02-12T14:45:23.000Z",
            "id": "1492510101684453381",
            "name": "Mike Bohan",
            "username": "TheMacsDaddy1"
        },
        {
            "created_at": "2022-02-12T14:48:11.000Z",
            "id": "1492510679814877188",
            "name": "Pierre Proucel",
            "username": "proucel"
        },
        {
            "created_at": "2022-02-12T14:44:05.000Z",
            "id": "1492509625543172096",
            "name": "Amit kumar singh",
            "username": "psnjsr19"
        },
        {
            "created_at": "2022-02-12T14:46:59.000Z",
            "id": "1492510451149971460",
            "name": "Murad Ali",
            "username": "MuradAl08290654"
        },
        {
            "created_at": "2022-02-07T12:55:56.000Z",
            "id": "1490670639325532166",
            "name": "Hancockrr3337",
            "username": "Hancock91077069"
        },
        {
            "created_at": "2022-02-12T14:44:32.000Z",
            "id": "1492509866870644736",
            "name": "Nimcan Aden Ahmed",
            "username": "NimcanAdenAhme1"
        },
        {
            "created_at": "2022-02-12T14:46:59.000Z",
            "id": "1492510479239073798",
            "name": "mhmdmrd",
            "username": "Muhamme69406968"
        },
        {
            "created_at": "2021-04-05T05:23:43.000Z",
            "id": "1378941335441436677",
            "name": "Palazoglu",
            "username": "Mdkazemi1"
        },
        {
            "created_at": "2022-02-12T14:43:05.000Z",
            "id": "1492509473243484160",
            "name": "Ray TS",
            "username": "Ray_0990"
        },
        {
            "created_at": "2022-02-12T14:48:50.000Z",
            "id": "1492510969796435973",
            "name": "Tudorgtaonline",
            "username": "tudorgtaonline"
        },
        {
            "created_at": "2022-02-11T19:57:45.000Z",
            "id": "1492226300685295616",
            "name": "MOHAMMED TIJJANI",
            "username": "Mtijjani305"
        },
        {
            "created_at": "2022-02-12T14:39:42.000Z",
            "id": "1492508644025552898",
            "name": "Luis Franco",
            "username": "LFrancoOfixial"
        },
        {
            "created_at": "2022-02-12T14:33:35.000Z",
            "id": "1492507080846196738",
            "name": "Mark Stubblefield",
            "username": "MarkDstu8"
        },
        {
            "created_at": "2022-02-12T14:34:05.000Z",
            "id": "1492507122176708608",
            "name": "Aman Kumar",
            "username": "AmanKum58622133"
        },
        {
            "created_at": "2022-02-12T14:48:14.000Z",
            "id": "1492510727877406724",
            "name": "More More",
            "username": "MoreMor44965070"
        },
        {
            "created_at": "2022-02-06T14:06:43.000Z",
            "id": "1490326057333006337",
            "name": "t gh b",
            "username": "tghb47666844"
        },
        {
            "created_at": "2022-02-12T14:42:24.000Z",
            "id": "1492509273565270017",
            "name": "GOLDI KUMAR",
            "username": "GOLDIKU00238142"
        },
        {
            "created_at": "2022-02-12T14:43:08.000Z",
            "id": "1492509495335006210",
            "name": "İsmet Akgül",
            "username": "Ismet_Akgul_"
        },
        {
            "created_at": "2022-02-12T11:46:04.000Z",
            "id": "1492464982906204163",
            "name": "a h澳",
            "username": "ah34330334"
        },
        {
            "created_at": "2022-02-02T17:46:09.000Z",
            "id": "1488931667721003019",
            "name": "Mirjalol Turdaliyev",
            "username": "Mirjalol2002"
        },
        {
            "created_at": "2022-02-12T14:38:51.000Z",
            "id": "1492508367335886850",
            "name": "Mervin Thomas",
            "username": "MervinThomas15"
        },
        {
            "created_at": "2022-02-12T14:44:37.000Z",
            "id": "1492509907886952449",
            "name": "Lokesky",
            "username": "Lokesky555"
        },
        {
            "created_at": "2010-04-16T05:18:23.000Z",
            "id": "133596141",
            "name": "喜马拉雅(夏小🦅🦅)",
            "username": "xiaxiaoyingying"
        },
        {
            "created_at": "2022-01-24T15:06:11.000Z",
            "id": "1485629820906184706",
            "name": "AnsariMohin",
            "username": "Ansari1_Mohin"
        },
        {
            "created_at": "2020-10-24T16:49:08.000Z",
            "id": "1320044599826649088",
            "name": "AlcyoneTheSailingBoat",
            "username": "SaveAlcyone"
        },
        {
            "created_at": "2011-03-30T21:14:01.000Z",
            "id": "274687788",
            "name": "abdulrahman Abdin",
            "username": "aboda1988"
        },
        {
            "created_at": "2022-02-12T13:56:15.000Z",
            "id": "1492497733244100610",
            "name": "nft.Boy.xxxgamer",
            "username": "Nft_xxx_gamer"
        },
        {
            "created_at": "2021-06-14T04:58:49.000Z",
            "id": "1404302236294000641",
            "name": "Peter Zalesak",
            "username": "PeterZalesak"
        },
        {
            "created_at": "2022-02-12T14:46:26.000Z",
            "id": "1492510297634091017",
            "name": "Mehran Ghanavati",
            "username": "behzaddadvar85"
        },
        {
            "created_at": "2022-02-12T14:44:35.000Z",
            "id": "1492509884302176257",
            "name": "Luna",
            "username": "Luna01978430"
        },
        {
            "created_at": "2022-02-12T14:45:33.000Z",
            "id": "1492510064833400839",
            "name": "Calogero Cascio",
            "username": "calogerocascio1"
        },
        {
            "created_at": "2021-12-09T03:13:36.000Z",
            "id": "1468780733460324355",
            "name": "Goat1331",
            "username": "Goat1331"
        },
        {
            "created_at": "2022-02-12T14:46:32.000Z",
            "id": "1492510328067866629",
            "name": "Kaden Board",
            "username": "KadenBoard"
        },
        {
            "created_at": "2017-10-28T21:43:18.000Z",
            "id": "924391144955531265",
            "name": "diallo",
            "username": "diallo19623880"
        },
        {
            "created_at": "2022-02-12T14:38:20.000Z",
            "id": "1492507936815468552",
            "name": "Destiny Kehinde",
            "username": "destiny_kehinde"
        },
        {
            "created_at": "2021-12-25T19:37:37.000Z",
            "id": "1474826531620851712",
            "name": "Hideing Gamer",
            "username": "GamerHideing"
        },
        {
            "created_at": "2022-02-12T14:40:47.000Z",
            "id": "1492508867913465859",
            "name": "Shazfa Rudianto",
            "username": "rudianto_sapar"
        },
        {
            "created_at": "2022-02-10T04:29:35.000Z",
            "id": "1491630306830733320",
            "name": "NAHIM",
            "username": "nahim0704"
        },
        {
            "created_at": "2022-01-17T16:19:17.000Z",
            "id": "1483111611976060934",
            "name": "ProfDrDong",
            "username": "ProfDrDong"
        },
        {
            "created_at": "2022-02-12T14:47:43.000Z",
            "id": "1492510695874781186",
            "name": "mleczu",
            "username": "mleczu3"
        },
        {
            "created_at": "2022-01-07T06:40:46.000Z",
            "id": "1479342123203940352",
            "name": "Validol",
            "username": "Validol76151291"
        },
        {
            "created_at": "2022-02-12T14:42:21.000Z",
            "id": "1492509351487340548",
            "name": "marukonen",
            "username": "marukonen07"
        },
        {
            "created_at": "2022-02-06T11:39:05.000Z",
            "id": "1490288605352574976",
            "name": "Dhinesh Sidhu",
            "username": "dhinesh__sidhu"
        },
        {
            "created_at": "2016-10-25T19:37:16.000Z",
            "id": "791000695449145344",
            "name": "Matthew Seles",
            "username": "mattsels0214"
        },
        {
            "created_at": "2022-02-09T16:09:21.000Z",
            "id": "1491444032647548933",
            "name": "Shubham Thakur",
            "username": "Shubham66390861"
        },
        {
            "created_at": "2022-02-12T14:39:39.000Z",
            "id": "1492508462794031106",
            "name": "Ujjwal Sharma",
            "username": "us356805"
        },
        {
            "created_at": "2022-02-08T06:17:05.000Z",
            "id": "1490932606267179008",
            "name": "Kiran Kckc",
            "username": "kiran_kckc"
        },
        {
            "created_at": "2022-02-12T14:36:39.000Z",
            "id": "1492507863994015744",
            "name": "Jason Fortezza",
            "username": "4tezza"
        },
        {
            "created_at": "2022-02-12T14:44:27.000Z",
            "id": "1492509867365576705",
            "name": "Abdullah Khurram",
            "username": "abdullah30067"
        },
        {
            "created_at": "2022-01-26T09:14:04.000Z",
            "id": "1486266079739809793",
            "name": "Bhakti Sagar",
            "username": "BhaktiS90603772"
        },
        {
            "created_at": "2022-02-12T14:44:15.000Z",
            "id": "1492509767948017666",
            "name": "Greenbean’s Tater-Tot Hut",
            "username": "GBTaterTotHut"
        },
        {
            "created_at": "2019-06-28T05:23:38.000Z",
            "id": "1144476427313508354",
            "name": "Krystal Franco",
            "username": "Krystal28997712"
        },
        {
            "created_at": "2012-02-03T19:09:55.000Z",
            "id": "482301636",
            "name": "Jinadu Abdulmumeen",
            "username": "Jinad93"
        },
        {
            "created_at": "2022-02-12T11:17:18.000Z",
            "id": "1492457740060528644",
            "name": "Stefan Noens",
            "username": "StefanNoens"
        }
    ],
    "meta": {
        "next_token": "BD1381JNSRN1EZZZ",
        "result_count": 100
    }
}